pyobjectocr/__init__.py
pyobjectocr-0.0.1.dist-info/licenses/LICENSE
pyobjectocr-0.0.1.dist-info/METADATA
pyobjectocr-0.0.1.dist-info/WHEEL
pyobjectocr-0.0.1.dist-info/top_level.txt
pyobjectocr-0.0.1.dist-info/RECORD
